lambda_deployment_test_utils/__init__.py
lambda_deployment_test_utils/pre_post_test_utils.py
aws_lambda_deployment_test_utils-0.0.13.dist-info/METADATA
aws_lambda_deployment_test_utils-0.0.13.dist-info/WHEEL
aws_lambda_deployment_test_utils-0.0.13.dist-info/top_level.txt
aws_lambda_deployment_test_utils-0.0.13.dist-info/zip-safe
aws_lambda_deployment_test_utils-0.0.13.dist-info/RECORD
